charimage
