Metadata-Version: 1.0
Name: charimage
Version: 0.3
Summary: convert black-white image to string which can be displayed in terminal.
Home-page: UNKNOWN
Author: cong liu
Author-email: shishusaiwai@vip.qq.com
License: GPL
Platform: UNKNOWN
